[
  {
    "section_id": "work-entry-analysis",
    "heading": "Work entry analysis",
    "product": "Odoo",
    "graph": {
      "entities": [
        {
          "name": "Odoo",
          "type": "Product",
          "mention": "Product: Odoo",
          "confidence": "high"
        },
        {
          "name": "Payroll app",
          "type": "Module",
          "mention": "Payroll app",
          "confidence": "high"
        },
        {
          "name": "Work Entry Analysis",
          "type": "Report",
          "mention": "default *Work Entries Analysis* report",
          "confidence": "high"
        },
        {
          "name": "Work Entry Type",
          "type": "Concept",
          "mention": "Work Entry Type",
          "confidence": "high"
        },
        {
          "name": "Employee",
          "type": "Concept",
          "mention": "Employee",
          "confidence": "high"
        },
        {
          "name": "Department",
          "type": "Concept",
          "mention": "Department",
          "confidence": "high"
        },
        {
          "name": "Company",
          "type": "Concept",
          "mention": "Company",
          "confidence": "high"
        },
        {
          "name": "validated work entries",
          "type": "DataObject",
          "mention": "validated work entries",
          "confidence": "medium"
        },
        {
          "name": "current month",
          "type": "Concept",
          "mention": "Current month",
          "confidence": "medium"
        },
        {
          "name": "pivot table",
          "type": "Concept",
          "mention": "pivot table",
          "confidence": "medium"
        },
        {
          "name": "work_entries",
          "type": "DataObject",
          "mention": "work_entries",
          "confidence": "medium"
        }
      ],
      "relations": [
        {
          "source": "Work Entry Analysis",
          "relation": "BELONGS_TO",
          "target": "Payroll app",
          "evidence": "To view this report, navigate to Payroll app --> Reporting --> Work Entry Analysis."
        },
        {
          "source": "Work Entry Analysis",
          "relation": "GENERATES",
          "target": "validated work entries",
          "evidence": "provides an overview of the validated work entries"
        },
        {
          "source": "Work Entry Analysis",
          "relation": "CONTAINS",
          "target": "Work Entry Type",
          "evidence": "The default options are Work Entry Type"
        },
        {
          "source": "Work Entry Analysis",
          "relation": "CONTAINS",
          "target": "Employee",
          "evidence": "The default options are Work Entry Type, Employee"
        },
        {
          "source": "Work Entry Analysis",
          "relation": "CONTAINS",
          "target": "Department",
          "evidence": "The default options are Work Entry Type, Employee, and Department"
        },
        {
          "source": "Work Entry Analysis",
          "relation": "CONTAINS",
          "target": "Company",
          "evidence": "If in a multi-company database, a Company option also appears."
        },
        {
          "source": "Payroll app",
          "relation": "IS_PART_OF",
          "target": "Odoo",
          "evidence": "Product: Odoo"
        }
      ]
    }
  },
  {
    "section_id": "work-entry-analysis-comparison",
    "heading": "Work entry analysis comparison",
    "product": "Odoo",
    "graph": {
      "entities": [
        {
          "name": "Odoo",
          "type": "Product",
          "mention": "Odoo",
          "confidence": "high"
        },
        {
          "name": "Payroll",
          "type": "Module",
          "mention": "Payroll app",
          "confidence": "high"
        },
        {
          "name": "Reporting",
          "type": "Sub-module",
          "mention": "Reporting",
          "confidence": "high"
        },
        {
          "name": "Work Entry Analysis",
          "type": "Report",
          "mention": "Work Entry Analysis",
          "confidence": "high"
        },
        {
          "name": "Work Entry Analysis comparison",
          "type": "Feature",
          "mention": "Work entry analysis comparison",
          "confidence": "high"
        },
        {
          "name": "Current Month: Previous Period",
          "type": "Setting",
          "mention": "Current Month: Previous Period",
          "confidence": "high"
        },
        {
          "name": "Current Month: Previous Year",
          "type": "Setting",
          "mention": "Current Month: Previous Year",
          "confidence": "high"
        },
        {
          "name": "Comparison column",
          "type": "Feature",
          "mention": "Comparison column",
          "confidence": "medium"
        },
        {
          "name": "Variation",
          "type": "Field",
          "mention": "Variation",
          "confidence": "medium"
        },
        {
          "name": "work entry type",
          "type": "DataObject",
          "mention": "work entry type",
          "confidence": "high"
        },
        {
          "name": "search bar",
          "type": "Feature",
          "mention": "search bar",
          "confidence": "low"
        },
        {
          "name": "fa-caret-down icon",
          "type": "Feature",
          "mention": "fa-caret-down (down arrow) icon",
          "confidence": "low"
        }
      ],
      "relations": [
        {
          "source": "Work Entry Analysis",
          "relation": "HAS_REPORT",
          "target": "Work Entry Analysis comparison",
          "evidence": "It is possible to compare the work entries..."
        },
        {
          "source": "Payroll",
          "relation": "CONTAINS",
          "target": "Reporting",
          "evidence": "navigate to Payroll app --> Reporting"
        },
        {
          "source": "Reporting",
          "relation": "CONTAINS",
          "target": "Work Entry Analysis",
          "evidence": "Reporting --> Work Entry Analysis"
        },
        {
          "source": "Work Entry Analysis comparison",
          "relation": "ENABLES",
          "target": "Current Month: Previous Period",
          "evidence": "click on either Current Month: Previous Period..."
        },
        {
          "source": "Work Entry Analysis comparison",
          "relation": "ENABLES",
          "target": "Current Month: Previous Year",
          "evidence": "click on either Current Month: Previous Year..."
        },
        {
          "source": "Work Entry Analysis comparison",
          "relation": "GENERATES",
          "target": "Variation",
          "evidence": "displays...the Variation between the two"
        },
        {
          "source": "Work Entry Analysis",
          "relation": "BELONGS_TO",
          "target": "Odoo",
          "evidence": "Product: Odoo"
        },
        {
          "source": "Work Entry Analysis comparison",
          "relation": "REQUIRES",
          "target": "work entry type",
          "evidence": "If no work entries for a specific work entry type..."
        },
        {
          "source": "Work Entry Analysis comparison",
          "relation": "REQUIRES",
          "target": "search bar filter",
          "evidence": "if the default Current month: filter is removed...the Comparison column does not appear"
        },
        {
          "source": "Work Entry Analysis comparison",
          "relation": "RELATED_TO",
          "target": "Comparison column",
          "evidence": "the Comparison column does not appear"
        }
      ]
    }
  },
  {
    "section_id": "use-case:-overtime-report-comparison",
    "heading": "Use case: overtime report comparison",
    "product": "Odoo",
    "graph": {
      "entities": [
        {
          "name": "Odoo",
          "type": "Product",
          "mention": "Product: Odoo",
          "confidence": "high"
        },
        {
          "name": "Payroll app",
          "type": "Module",
          "mention": "Payroll app",
          "confidence": "high"
        },
        {
          "name": "Reporting",
          "type": "Module",
          "mention": "Reporting",
          "confidence": "medium"
        },
        {
          "name": "Work Entry Analysis",
          "type": "Report",
          "mention": "Work Entry Analysis",
          "confidence": "high"
        },
        {
          "name": "Work Entries Analysis",
          "type": "Report",
          "mention": "Work Entries Analysis",
          "confidence": "medium"
        },
        {
          "name": "Work Entry Type",
          "type": "DataObject",
          "mention": "Work Entry Type",
          "confidence": "high"
        },
        {
          "name": "Overtime Hours",
          "type": "Field",
          "mention": "Overtime Hours",
          "confidence": "high"
        },
        {
          "name": "Add Custom Filter",
          "type": "Action",
          "mention": "Add Custom Filter",
          "confidence": "high"
        },
        {
          "name": "Employee",
          "type": "Field",
          "mention": "Employee",
          "confidence": "high"
        },
        {
          "name": "Marc Demo",
          "type": "Actor",
          "mention": "Marc Demo",
          "confidence": "high"
        },
        {
          "name": "Beth Evans",
          "type": "Actor",
          "mention": "Beth Evans",
          "confidence": "high"
        },
        {
          "name": "Mitchell Admin",
          "type": "Actor",
          "mention": "Mitchell Admin",
          "confidence": "high"
        }
      ],
      "relations": [
        {
          "source": "Work Entry Analysis",
          "relation": "IS_PART_OF",
          "target": "Reporting",
          "evidence": "To view this data, first navigate to the default *Work entry analysis* report by going to Payroll app --> Reporting --> Work Entry Analysis."
        },
        {
          "source": "Reporting",
          "relation": "IS_PART_OF",
          "target": "Payroll app",
          "evidence": "To view this data, first navigate to the default *Work entry analysis* report by going to Payroll app --> Reporting --> Work Entry Analysis."
        },
        {
          "source": "Payroll app",
          "relation": "BELONGS_TO",
          "target": "Odoo",
          "evidence": "Product: Odoo. To view this data, first navigate to the default *Work entry analysis* report by going to Payroll app --> Reporting --> Work Entry Analysis."
        },
        {
          "source": "Work Entry Analysis",
          "relation": "PRODUCES",
          "target": "Overtime Hours",
          "evidence": "Now, the report displays the Overtime Hours for the current month and the previous month"
        },
        {
          "source": "Work Entry Analysis",
          "relation": "CONTAINS",
          "target": "Work Entry Type",
          "evidence": "Using the drop-down menu, select Work Entry Type for the first field"
        },
        {
          "source": "Work Entry Type",
          "relation": "CONTAINS",
          "target": "Overtime Hours",
          "evidence": "and select Overtime Hours for the last field"
        },
        {
          "source": "Work Entry Analysis",
          "relation": "CONTAINS",
          "target": "Employee",
          "evidence": "Click Employee, and all employees with overtime work entries for either the current or previous month appears"
        },
        {
          "source": "Work Entry Analysis",
          "relation": "CONFIGURED_BY",
          "target": "Add Custom Filter",
          "evidence": "Under the fa-filter Filters column, click Add Custom Filter"
        },
        {
          "source": "Marc Demo",
          "relation": "RELATED_TO",
          "target": "Work Entry Analysis",
          "evidence": "In this example, it can be determined that Marc Demo worked the most overtime"
        },
        {
          "source": "Beth Evans",
          "relation": "RELATED_TO",
          "target": "Work Entry Analysis",
          "evidence": "Beth Evans worked the most overtime hours"
        },
        {
          "source": "Mitchell Admin",
          "relation": "RELATED_TO",
          "target": "Work Entry Analysis",
          "evidence": "Mitchell Admin had the largest variation change"
        }
      ]
    }
  }
]