[
  {
    "section_id": "configuration",
    "heading": "Configuration",
    "product": "Odoo",
    "graph": {
      "entities": [
        {
          "name": "Odoo",
          "type": "Product",
          "mention": "Odoo",
          "confidence": "high"
        },
        {
          "name": "Hong Kong - Accounting",
          "type": "Module",
          "mention": "Hong Kong - Accounting",
          "confidence": "high"
        },
        {
          "name": "l10n_hk",
          "type": "Module",
          "mention": "`l10n_hk`",
          "confidence": "high"
        },
        {
          "name": "Hong Kong - Payroll",
          "type": "Module",
          "mention": "Hong Kong - Payroll",
          "confidence": "high"
        },
        {
          "name": "l10n_hk_hr_payroll",
          "type": "Module",
          "mention": "`l10n_hk_hr_payroll`",
          "confidence": "high"
        },
        {
          "name": "Payroll",
          "type": "Module",
          "mention": "*Payroll* app",
          "confidence": "high"
        },
        {
          "name": "Hong Kong - Payroll with Accounting",
          "type": "Module",
          "mention": "Hong Kong - Payroll with Accounting",
          "confidence": "high"
        },
        {
          "name": "l10n_hk_hr_payroll_account",
          "type": "Module",
          "mention": "`l10n_hk_hr_payroll_account`",
          "confidence": "high"
        },
        {
          "name": "Documents - Hong Kong Payroll",
          "type": "Module",
          "mention": "Documents - Hong Kong Payroll",
          "confidence": "high"
        },
        {
          "name": "documents_l10n_hk_hr_payroll",
          "type": "Module",
          "mention": "`documents_l10n_hk_hr_payroll`",
          "confidence": "high"
        },
        {
          "name": "Documents",
          "type": "Module",
          "mention": "Odoo *Documents* app",
          "confidence": "high"
        },
        {
          "name": "employee ir56 forms",
          "type": "DataObject",
          "mention": "employee ir56 forms",
          "confidence": "medium"
        }
      ],
      "relations": [
        {
          "source": "Hong Kong - Accounting",
          "relation": "IS_PART_OF",
          "target": "Odoo",
          "evidence": "Install ... the following modules to get the latest features of the Hong Kong localization"
        },
        {
          "source": "Hong Kong - Payroll",
          "relation": "IS_PART_OF",
          "target": "Odoo",
          "evidence": "Install ... the following modules to get the latest features of the Hong Kong localization"
        },
        {
          "source": "Hong Kong - Payroll with Accounting",
          "relation": "IS_PART_OF",
          "target": "Odoo",
          "evidence": "Install ... the following modules to get the latest features of the Hong Kong localization"
        },
        {
          "source": "Documents - Hong Kong Payroll",
          "relation": "IS_PART_OF",
          "213": "Odoo",
          "evidence": "Install ... the following modules to get the latest features of the Hong Kong localization"
        },
        {
          "source": "Hong Kong - Payroll",
          "relation": "HAS_FEATURE",
          "target": "payroll specific localization features",
          "evidence": "Enables payroll <payroll/l10n_hk/payroll> specific localization features"
        },
        {
          "source": "Hong Kong - Payroll",
          "relation": "BELONGS_TO",
          "target": "Payroll",
          "evidence": "Enables payroll specific localization features for Odoo *Payroll* app"
        },
        {
          "source": "Hong Kong - Payroll",
          "relation": "CONTAINS",
          "target": "Hong Kong - Payroll with Accounting",
          "evidence": "This module also installs Hong Kong - Payroll with Accounting"
        },
        {
          "source": "Hong Kong - Payroll",
          "relation": "CONTAINS",
          "target": "Documents - Hong Kong Payroll",
          "evidence": "This module also installs Hong Kong - Payroll with Accounting and Documents - Hong Kong Payroll"
        },
        {
          "source": "Hong Kong - Payroll with Accounting",
          "relation": "HAS_FEATURE",
          "target": "link between Hong Kong payroll and accounting",
          "evidence": "Installs the link between Hong Kong payroll and accounting"
        },
        {
          "source": "Documents - Hong Kong Payroll",
          "relation": "BELONGS_TO",
          "target": "Documents",
          "evidence": "Integrates employee ir56 forms in the Odoo *Documents* app"
        },
        {
          "source": "Documents - Hong Kong Payroll",
          "relation": "CONTAINS",
          "target": "employee ir56 forms",
          "evidence": "Integrates employee ir56 forms in the Odoo *Documents* app"
        }
      ]
    }
  },
  {
    "section_id": "fps-qr-codes-on-invoices",
    "heading": "FPS QR codes on invoices",
    "product": "Odoo",
    "graph": {
      "entities": [
        {
          "name": "Odoo",
          "type": "Product",
          "mention": "Product",
          "confidence": "high"
        },
        {
          "name": "FPS QR codes on invoices",
          "type": "Feature",
          "mention": "Title",
          "confidence": "high"
        },
        {
          "name": "Faster Payment System",
          "type": "Module",
          "mention": "FPS",
          "confidence": "high"
        }
      ],
      "relations": [
        {
          "source": "FPS QR codes on invoices",
          "relation": "IS_PART_OF",
          "target": "Odoo",
          "evidence": "Product: Odoo"
        },
        {
          "source": "Faster Payment System",
          "relation": "CONTAINS",
          "target": "FPS QR codes on invoices",
          "evidence": "Title: FPS QR codes on invoices"
        }
      ]
    }
  },
  {
    "section_id": "activate-qr-codes",
    "heading": "Activate QR codes",
    "product": "Odoo",
    "graph": {
      "entities": [
        {
          "name": "Odoo",
          "type": "Product",
          "mention": "Odoo",
          "confidence": "high"
        },
        {
          "name": "Accounting",
          "type": "Module",
          "mention": "Accounting app",
          "confidence": "high"
        },
        {
          "name": "Configuration",
          "type": "Module",
          "mention": "Configuration",
          "confidence": "high"
        },
        {
          "name": "Settings",
          "type": "Setting",
          "mention": "Settings",
          "confidence": "high"
        },
        {
          "name": "Customer Payments",
          "type": "Sub-module",
          "mention": "Customer Payments section",
          "confidence": "high"
        },
        {
          "name": "QR Codes feature",
          "type": "Feature",
          "mention": "QR Codes feature",
          "confidence": "high"
        },
        {
          "name": "Save",
          "type": "Action",
          "mention": "click Save",
          "confidence": "high"
        }
      ],
      "relations": [
        {
          "source": "Accounting",
          "relation": "CONTAINS",
          "target": "Configuration",
          "evidence": "Go to Accounting app --> Configuration"
        },
        {
          "source": "Configuration",
          "relation": "CONTAINS",
          "target": "Settings",
          "evidence": "Configuration --> Settings"
        },
        {
          "source": "Settings",
          "relation": "CONTAINS",
          "target": "Customer Payments",
          "evidence": "Under the Customer Payments section"
        },
        {
          "source": "Customer Payments",
          "relation": "HAS_FEATURE",
          "target": "QR Codes feature",
          "evidence": "Under the Customer Payments section, tick the checkbox beside the QR Codes feature"
        },
        {
          "source": "QR Codes feature",
          "relation": "CONFIGURED_BY",
          "target": "Settings",
          "evidence": "Under the Customer Payments section, tick the checkbox beside the QR Codes feature"
        },
        {
          "source": "Save",
          "relation": "PERFORMED_BY",
          "target": "Unknown",
          "evidence": "Then, click Save"
        }
      ]
    }
  },
  {
    "section_id": "fps-bank-account-configuration",
    "heading": "FPS bank account configuration",
    "product": "Odoo",
    "graph": {
      "entities": [
        {
          "name": "Odoo",
          "type": "Product",
          "mention": "Product: Odoo",
          "confidence": "high"
        },
        {
          "name": "Contacts app",
          "type": "Module",
          "mention": "Contacts app",
          "confidence": "medium"
        },
        {
          "name": "Configuration",
          "type": "Sub-module",
          "mention": "Configuration",
          "confidence": "medium"
        },
        {
          "name": "Bank Accounts section",
          "type": "Sub-module",
          "mention": "Bank Accounts section",
          "confidence": "medium"
        },
        {
          "name": "Bank Accounts",
          "type": "Module",
          "mention": "Bank Accounts",
          "confidence": "medium"
        },
        {
          "name": "FPS activation",
          "type": "Action",
          "mention": "FPS activation",
          "confidence": "medium"
        },
        {
          "name": "Proxy Type",
          "type": "Field",
          "mention": "Proxy Type",
          "confidence": "high"
        },
        {
          "name": "Proxy Value",
          "type": "Field",
          "mention": "Proxy Value",
          "confidence": "high"
        },
        {
          "name": "QR code",
          "type": "DataObject",
          "mention": "QR code",
          "confidence": "medium"
        },
        {
          "name": "invoice number",
          "type": "Field",
          "mention": "invoice number",
          "confidence": "medium"
        },
        {
          "name": "Include Reference checkbox",
          "type": "Setting",
          "mention": "Include Reference checkbox",
          "confidence": "medium"
        },
        {
          "name": "account holder",
          "type": "Actor",
          "mention": "account holder",
          "confidence": "medium"
        },
        {
          "name": "country",
          "type": "Field",
          "mention": "country",
          "confidence": "medium"
        },
        {
          "name": "Hong Kong",
          "type": "Concept",
          "mention": "Hong Kong",
          "confidence": "medium"
        },
        {
          "name": "contact form",
          "type": "DataObject",
          "mention": "contact form",
          "confidence": "medium"
        },
        {
          "name": "city",
          "type": "Field",
          "mention": "city",
          "confidence": "medium"
        },
        {
          "name": "../accounting/bank",
          "type": "Concept",
          "mention": "../accounting/bank",
          "confidence": "low"
        }
      ],
      "relations": [
        {
          "source": "Contacts app",
          "relation": "CONTAINS",
          "target": "Configuration",
          "evidence": "Go to Contacts app --> Configuration"
        },
        {
          "source": "Configuration",
          "relation": "CONTAINS",
          "target": "Bank Accounts section",
          "evidence": "Configuration --> Bank Accounts section"
        },
        {
          "source": "Bank Accounts section",
          "relation": "CONTAINS",
          "target": "Bank Accounts",
          "evidence": "Bank Accounts section --> Bank Accounts"
        },
        {
          "source": "Bank Accounts",
          "relation": "HAS_FEATURE",
          "target": "FPS activation",
          "evidence": "select the bank account for FPS activation"
        },
        {
          "source": "Bank Accounts",
          "relation": "CONFIGURED_BY",
          "target": "Proxy Type",
          "evidence": "set the Proxy Type"
        },
        {
          "source": "Bank Accounts",
          "relation": "CONFIGURED_BY",
          "target": "Proxy Value",
          "evidence": "fill in the Proxy Value field"
        },
        {
          "source": "QR code",
          "relation": "CONFIGURED_BY",
          "target": "Include Reference checkbox",
          "evidence": "by ticking the Include Reference checkbox"
        },
        {
          "source": "QR code",
          "relation": "CONTAINS",
          "target": "invoice number",
          "evidence": "include the invoice number in the QR code"
        },
        {
          "source": "account holder",
          "relation": "PERFORMED_BY",
          "target": "country",
          "evidence": "account holder's country"
        },
        {
          "source": "account holder",
          "relation": "PERFORMED_BY",
          "target": "city",
          "evidence": "account holder's city"
        },
        {
          "source": "country",
          "relation": "IS_PART_OF",
          "target": "contact form",
          "evidence": "set on its contact form"
        },
        {
          "source": "city",
          "relation": "IS_PART_OF",
          "target": "contact form",
          "evidence": "set on its contact form"
        },
        {
          "source": "Hong Kong",
          "type": "Concept",
          "mention": "Hong Kong",
          "confidence": "medium"
        },
        {
          "source": "contact form",
          "type": "DataObject",
          "mention": "contact form",
          "confidence": "medium"
        },
        {
          "source": "../accounting/bank",
          "type": "Concept",
          "mention": "../accounting/bank",
          "confidence": "low"
        },
        {
          "source": "../accounting/bank",
          "relation": "SEE_ALSO",
          "target": "../accounting/bank",
          "evidence": "../accounting/bank"
        }
      ]
    }
  },
  {
    "section_id": "bank-journal-configuration",
    "heading": "Bank journal configuration",
    "product": "Odoo",
    "graph": {
      "entities": [
        {
          "name": "Odoo",
          "type": "Product",
          "mention": "Odoo",
          "confidence": "high"
        },
        {
          "name": "Accounting",
          "type": "Module",
          "mention": "Accounting app",
          "confidence": "high"
        },
        {
          "name": "Configuration",
          "type": "Sub-module",
          "mention": "Configuration",
          "confidence": "medium"
        },
        {
          "name": "Journals",
          "type": "Sub-module",
          "mention": "Journals",
          "confidence": "high"
        },
        {
          "name": "Bank journal",
          "type": "DataObject",
          "mention": "bank journal",
          "confidence": "high"
        },
        {
          "name": "Account Number",
          "type": "Field",
          "mention": "Account Number",
          "confidence": "high"
        },
        {
          "name": "Bank",
          "type": "Field",
          "mention": "Bank",
          "confidence": "high"
        },
        {
          "name": "Journal Entries tab",
          "type": "Sub-module",
          "mention": "Journal Entries tab",
          "confidence": "medium"
        }
      ],
      "relations": [
        {
          "source": "Accounting",
          "relation": "CONTAINS",
          "target": "Configuration",
          "evidence": "Accounting app --> Configuration"
        },
        {
          "source": "Configuration",
          "relation": "CONTAINS",
          "target": "Journals",
          "evidence": "Configuration --> Journals"
        },
        {
          "source": "Journals",
          "relation": "CONTAINS",
          "target": "Bank journal",
          "evidence": "open the bank journal"
        },
        {
          "source": "Bank journal",
          "relation": "CONTAINS",
          "target": "Journal Entries tab",
          "evidence": "located in the Journal Entries tab"
        },
        {
          "source": "Journal Entries tab",
          "relation": "CONTAINS",
          "target": "Account Number",
          "evidence": "located in the Journal Entries tab"
        },
        {
          "source": "Journal Entries tab",
          "relation": "CONTAINS",
          "target": "Bank",
          "evidence": "located in the Journal Entries tab"
        }
      ]
    }
  },
  {
    "section_id": "issue-invoices-with-fps-qr-codes",
    "heading": "Issue invoices with FPS QR codes",
    "product": "Odoo",
    "graph": {
      "entities": [
        {
          "name": "Odoo",
          "type": "Product",
          "mention": "Odoo",
          "confidence": "high"
        },
        {
          "name": "Invoice",
          "type": "DataObject",
          "mention": "invoice",
          "confidence": "high"
        },
        {
          "name": "Other Info tab",
          "type": "Module",
          "mention": "Other Info tab",
          "confidence": "medium"
        },
        {
          "name": "Payment QR-code option",
          "type": "Field",
          "mention": "Payment QR-code option",
          "confidence": "high"
        },
        {
          "name": "EMV Merchant-Presented QR-code",
          "type": "Feature",
          "mention": "EMV Merchant-Presented QR-code",
          "confidence": "high"
        },
        {
          "name": "Recipient Bank",
          "type": "Field",
          "mention": "Recipient Bank",
          "confidence": "high"
        },
        {
          "name": "FPS QR code",
          "type": "Feature",
          "mention": "FPS QR code",
          "confidence": "high"
        }
      ],
      "relations": [
        {
          "source": "Invoice",
          "relation": "IS_PART_OF",
          "target": "Odoo",
          "evidence": "Issue invoices with FPS QR codes"
        },
        {
          "source": "Other Info tab",
          "relation": "IS_PART_OF",
          "target": "Invoice",
          "evidence": "open the Other Info tab"
        },
        {
          "source": "Invoice",
          "relation": "CONTAINS",
          "target": "Payment QR-code option",
          "evidence": "set the Payment QR-code option"
        },
        {
          "source": "Payment QR-code option",
          "relation": "CONFIGURED_BY",
          "target": "EMV Merchant-Presented QR-code",
          "evidence": "set the Payment QR-code option to EMV Merchant-Presented QR-code"
        },
        {
          "source": "Invoice",
          "relation": "CONTAINS",
          "target": "Recipient Bank",
          "evidence": "Ensure that the Recipient Bank is configured"
        },
        {
          "source": "Odoo",
          "relation": "ENABLES",
          "target": "FPS QR code",
          "evidence": "Odoo uses this field to generate the FPS QR code"
        },
        {
          "source": "FPS QR code",
          "relation": "REQUIRES",
          "target": "Recipient Bank",
          "evidence": "Odoo uses this field to generate the FPS QR code"
        }
      ]
    }
  }
]