[
  {
    "section_id": "submit-expenses",
    "heading": "Submit expenses",
    "product": "Odoo",
    "graph": {
      "entities": [
        {
          "name": "Odoo",
          "type": "Product",
          "mention": "Odoo",
          "confidence": "high"
        },
        {
          "name": "Submit expenses",
          "type": "Action",
          "mention": "Submit expenses",
          "confidence": "high"
        },
        {
          "name": "log expenses",
          "type": "Action",
          "mention": "log_expenses",
          "confidence": "high"
        }
      ],
      "relations": [
        {
          "source": "Submit expenses",
          "relation": "TRIGGERED_BY",
          "target": "log expenses",
          "evidence": "When expenses have been logged the next step is to submit them for approval"
        },
        {
          "source": "Submit expenses",
          "relation": "ENABLES",
          "target": "Reimbursement",
          "evidence": "so the expenses can then be reimbursed"
        },
        {
          "source": "Submit expenses",
          "relation": "BELONGS_TO",
          "target": "Odoo",
          "evidence": "Product: Odoo Title: Submit expenses"
        }
      ]
    }
  },
  {
    "section_id": "my-expenses-dashboard",
    "heading": "My expenses dashboard",
    "product": "Odoo",
    "graph": {
      "entities": [
        {
          "name": "Odoo",
          "type": "Product",
          "mention": "Odoo",
          "confidence": "high"
        },
        {
          "name": "Expenses",
          "type": "Module",
          "mention": "Expenses app",
          "confidence": "high"
        },
        {
          "name": "My Expenses dashboard",
          "type": "Module",
          "mention": "My Expenses dashboard",
          "confidence": "high"
        },
        {
          "name": "My Expenses",
          "type": "Sub-module",
          "mention": "My Expenses",
          "confidence": "high"
        },
        {
          "name": "Submit button",
          "type": "Action",
          "mention": "Submit button",
          "confidence": "high"
        },
        {
          "name": "Draft",
          "type": "Status",
          "mention": "Draft",
          "confidence": "high"
        },
        {
          "name": "Submitted",
          "type": "Status",
          "mention": "Submitted",
          "confidence": "high"
        },
        {
          "name": "Approved",
          "type": "Status",
          "mention": "Approved",
          "confidence": "high"
        },
        {
          "name": "Refused",
          "type": "Status",
          "mention": "Refused",
          "confidence": "high"
        },
        {
          "name": "To Submit",
          "type": "Field",
          "mention": "To Submit field",
          "confidence": "medium"
        },
        {
          "name": "Waiting Approval",
          "type": "Field",
          "mention": "Waiting Approval amount",
          "confidence": "medium"
        },
        {
          "name": "Waiting Reimbursement",
          "type": "Field",
          "mention": "Waiting Reimbursement total",
          "confidence": "medium"
        },
        {
          "name": "Employee",
          "type": "Actor",
          "mention": "Employee",
          "confidence": "medium"
        }
      ],
      "relations": [
        {
          "source": "Expenses",
          "relation": "CONTAINS",
          "target": "My Expenses dashboard",
          "evidence": "Navigate to Expenses app --> My Expenses --> My Expenses."
        },
        {
          "source": "My Expenses dashboard",
          "relation": "CONTAINS",
          "target": "My Expenses",
          "evidence": "Navigate to Expenses app --> My Expenses --> My Expenses."
        },
        {
          "source": "Expenses",
          "relation": "CONTAINS",
          "target": "My Expenses",
          "evidence": "Navigate to Expenses app --> My Expenses --> My Expenses."
        },
        {
          "source": "My Expenses dashboard",
          "relation": "HAS_REPORT",
          "target": "My Expenses",
          "evidence": "Displays the My Expenses dashboard, by default."
        },
        {
          "source": "My Expenses",
          "relation": "CONFIGURED_BY",
          "target": "Submit button",
          "evidence": "Submit button is only visible when expenses with a status of Draft are selected."
        },
        {
          "source": "Submit button",
          "relation": "PERFORMED_BY",
          "target": "Employee",
          "evidence": "Another way to select all expenses with a Draft status is to click...then click the checkbox next to Employee."
        },
        {
          "source": "Draft",
          "relation": "PRODUCES",
          "target": "To Submit",
          "evidence": "Expenses with a status of Draft are used to calculate the amount in the To Submit field."
        },
        {
          "source": "Submitted",
          "relation": "PRODUCES",
          "target": "Waiting Approval",
          "evidence": "Expenses with a status of Submitted are used to calculate the Waiting Approval amount."
        },
        {
          "source": "Approved",
          "relation": "PRODUCES",
          "target": "Waiting Reimbursement",
          "evidence": "Expenses with a status of Approved are used to calculate the Waiting Reimbursement total."
        }
      ]
    }
  },
  {
    "section_id": "submit-expense-records",
    "heading": "Submit expense records",
    "product": "Odoo",
    "graph": {
      "entities": [
        {
          "name": "Odoo",
          "type": "Product",
          "mention": "Product",
          "confidence": "high"
        },
        {
          "name": "My Expenses dashboard",
          "type": "Module",
          "mention": "On the My Expenses dashboard",
          "confidence": "medium"
        },
        {
          "name": "expenses",
          "type": "DataObject",
          "mention": "expense records",
          "confidence": "high"
        },
        {
          "name": "Submit button",
          "type": "Action",
          "mention": "click the Submit button",
          "confidence": "high"
        }
      ],
      "relations": [
        {
          "source": "expenses",
          "relation": "BELONGS_TO",
          "target": "My Expenses dashboard",
          "evidence": "On the My Expenses dashboard, select the desired expenses"
        },
        {
          "source": "Submit button",
          "relation": "PRODUCES",
          "target": "expenses",
          "evidence": "Once the expenses have been selected, click the Submit button"
        }
      ]
    }
  }
]